iotrelay_nest.py
iotrelay_nest-1.0.1.dist-info/DESCRIPTION.rst
iotrelay_nest-1.0.1.dist-info/METADATA
iotrelay_nest-1.0.1.dist-info/RECORD
iotrelay_nest-1.0.1.dist-info/WHEEL
iotrelay_nest-1.0.1.dist-info/entry_points.txt
iotrelay_nest-1.0.1.dist-info/metadata.json
iotrelay_nest-1.0.1.dist-info/top_level.txt
