Metadata-Version: 2.0
Name: iotrelay-nest
Version: 1.0.1
Summary: IoT Relay plugin for the Nest Thermostat
Home-page: https://github.com/eman/iotrelay-nest
Author: Emmanuel Levijarvi
Author-email: emansl@gmail.com
License: BSD
Keywords: IoT Relay Nest Temerature Humidity
Platform: UNKNOWN
Classifier: Development Status :: 4 - Beta
Classifier: Intended Audience :: Developers
Classifier: Topic :: Utilities
Classifier: License :: OSI Approved :: BSD License
Classifier: Operating System :: OS Independent
Classifier: Programming Language :: Python :: 2
Classifier: Programming Language :: Python :: 3
Requires-Dist: PyNest
Requires-Dist: iotrelay
